SPINAL_TEST/tmp/job_1/Emif_Ctrl_test.v
// Generator : SpinalHDL v1.6.0    git head : 73c8d8e2b86b45646e9d0b2e729291f2b65e6be3
// Component : Emif_Ctrl_test
// Git hash  : aa52522608eb231392ebc67a74accdba89f54e2c



module Emif_Ctrl_test (
  input      [23:0]   emif_emif_addr,
  input      [31:0]   emif_emif_data_read,
  output     [31:0]   emif_emif_data_write,
  output              emif_emif_data_writeEnable,
  input               emif_emif_cs,
  input               emif_emif_we,
  input               emif_emif_oe,
  output     [19:0]   apb_PADDR,
  output     [0:0]    apb_PSEL,
  output              apb_PENABLE,
  input               apb_PREADY,
  output              apb_PWRITE,
  output     [31:0]   apb_PWDATA,
  input      [31:0]   apb_PRDATA,
  input               apb_PSLVERROR,
  input               clk,
  input               reset
);
  reg                 penable;
  reg        [31:0]   emifdatatemp;
  reg                 penable_regNext;
  wire                when_EmifToApb_l69;
  wire                when_EmifToApb_l77;
  reg        [31:0]   apb_PRDATA_regNextWhen;

  assign apb_PADDR = emif_emif_addr[19:0];
  assign apb_PSEL = (~ emif_emif_cs);
  assign apb_PENABLE = ((penable && (! penable_regNext)) ? penable : 1'b0);
  assign apb_PWRITE = ((! emif_emif_we) && emif_emif_oe);
  assign when_EmifToApb_l69 = (((! emif_emif_we) && emif_emif_oe) && (! emif_emif_addr[23]));
  assign apb_PWDATA = emif_emif_data_read;
  assign emif_emif_data_writeEnable = (! emif_emif_oe);
  assign when_EmifToApb_l77 = (! emif_emif_oe);
  assign emif_emif_data_write = apb_PRDATA_regNextWhen;
  always @(posedge clk or posedge reset) begin
    if(reset) begin
      penable <= 1'b0;
    end else begin
      penable <= ((! emif_emif_oe) || (! emif_emif_we));
    end
  end

  always @(posedge clk) begin
    penable_regNext <= penable;
    if(when_EmifToApb_l69) begin
      emifdatatemp <= emif_emif_data_read;
    end
    if(when_EmifToApb_l77) begin
      apb_PRDATA_regNextWhen <= apb_PRDATA;
    end
  end


endmodule

SPINAL_TEST/simWorkspace/Emif_Ctrl_test/test.vcd
$version Generated by VerilatedVcd $end
$date Mon Aug 09 15:12:26 2021
 $end
$timescale   1ns $end

 $scope module TOP $end
  $var wire 20 { apb_PADDR [19:0] $end
  $var wire  1 -! apb_PENABLE $end
  $var wire 32 M! apb_PRDATA [31:0] $end
  $var wire  1 5! apb_PREADY $end
  $var wire  1 %! apb_PSEL [0:0] $end
  $var wire  1 U! apb_PSLVERROR $end
  $var wire 32 E! apb_PWDATA [31:0] $end
  $var wire  1 =! apb_PWRITE $end
  $var wire  1 ]! clk $end
  $var wire 24 C emif_emif_addr [23:0] $end
  $var wire  1 c emif_emif_cs $end
  $var wire 32 K emif_emif_data_read [31:0] $end
  $var wire 32 S emif_emif_data_write [31:0] $end
  $var wire  1 [ emif_emif_data_writeEnable $end
  $var wire  1 s emif_emif_oe $end
  $var wire  1 k emif_emif_we $end
  $var wire  1 e! reset $end
  $scope module Emif_Ctrl_test $end
   $var wire 20 { apb_PADDR [19:0] $end
   $var wire  1 -! apb_PENABLE $end
   $var wire 32 M! apb_PRDATA [31:0] $end
   $var wire 32 3 apb_PRDATA_regNextWhen [31:0] $end
   $var wire  1 5! apb_PREADY $end
   $var wire  1 %! apb_PSEL [0:0] $end
   $var wire  1 U! apb_PSLVERROR $end
   $var wire 32 E! apb_PWDATA [31:0] $end
   $var wire  1 =! apb_PWRITE $end
   $var wire  1 ]! clk $end
   $var wire 24 C emif_emif_addr [23:0] $end
   $var wire  1 c emif_emif_cs $end
   $var wire 32 K emif_emif_data_read [31:0] $end
   $var wire 32 S emif_emif_data_write [31:0] $end
   $var wire  1 [ emif_emif_data_writeEnable $end
   $var wire  1 s emif_emif_oe $end
   $var wire  1 k emif_emif_we $end
   $var wire 32 # emifdatatemp [31:0] $end
   $var wire  1 ; penable $end
   $var wire  1 + penable_regNext $end
   $var wire  1 e! reset $end
   $var wire  1 m! when_EmifToApb_l69 $end
   $var wire  1 u! when_EmifToApb_l77 $end
  $upscope $end
 $upscope $end
$enddefinitions $end


#0
b10100100011111011000110111010111 #
1+
b10100000001111100010100110011010 3
0;
b000000000000000000000000 C
b00010000001011000100111110100101 K
b10100000001111100010100110011010 S
0[
1c
1k
1s
b00000000000000000000 {
0%!
0-!
15!
0=!
b00010000001011000100111110100101 E!
b10010000111100111111111000101101 M!
1U!
0]!
1e!
0m!
0u!
#160
0e!
#170
0+
1]!
#175
0]!
#180
1]!
#185
0]!
#190
1]!
#195
0]!
#200
1]!
#205
0]!
#210
1]!
#215
0]!
#220
1]!
#225
0]!
#230
1]!
#235
0]!
#240
1]!
#245
0]!
#250
1]!
#255
0]!
#260
1]!
#265
0]!
#270
b000000000000000000000100 C
0c
b00000000000000000100 {
1%!
1]!
#275
0]!
#280
b00000000000000000101011001111000 K
0k
1=!
b00000000000000000101011001111000 E!
1]!
1m!
#285
0]!
#290
b00000000000000000101011001111000 #
1;
1-!
1]!
#295
0]!
#300
1+
1c
1k
0%!
0-!
0=!
1]!
0m!
#305
0]!
#310
0;
b100000000000000000000100 C
0c
1%!
1]!
#315
0]!
#320
0+
b00000000000000000001001000110100 K
0k
1=!
b00000000000000000001001000110100 E!
1]!
#325
0]!
#330
1;
1-!
1]!
#335
0]!
#340
1+
1c
1k
0%!
0-!
0=!
1]!
#345
0]!
#350
0;
b000000000000000000000000 C
0c
b00000000000000000000 {
1%!
1]!
#355
0]!
#360
0+
1[
0s
1]!
1u!
#365
0]!
#370
b10010000111100111111111000101101 3
1;
b10010000111100111111111000101101 S
1-!
1]!
#375
0]!
#380
1+
0[
1c
1s
0%!
0-!
1]!
0u!
#385
0]!
#390
0;
b100000000000000000000000 C
0c
1%!
1]!
#395
0]!
#400
0+
1[
0s
1]!
1u!
#405
0]!
#410
1;
1-!
1]!
#415
0]!
#420
1+
0[
1c
1s
0%!
0-!
1]!
0u!
#425
0]!
#430
0;
1]!
#435
0]!
#440
0+
1]!
