SPINAL_TEST/tmp/job_1/DataSync.v
// Generator : SpinalHDL v1.6.0    git head : 73c8d8e2b86b45646e9d0b2e729291f2b65e6be3
// Component : DataSync
// Git hash  : 65291426c6eb570603f2906aaddb1e59c5c7d9d9



module DataSync (
  input               clk_in,
  input               clk_out,
  input               reset,
  input               datain_valid,
  output              datain_ready,
  input      [15:0]   datain_payload,
  output     [15:0]   dataout
);
  wire                streamCCByToggle_1_io_input_ready;
  wire                streamCCByToggle_1_io_output_valid;
  wire       [15:0]   streamCCByToggle_1_io_output_payload;

  StreamCCByToggle streamCCByToggle_1 (
    .io_input_valid       (datain_valid                          ), //i
    .io_input_ready       (streamCCByToggle_1_io_input_ready     ), //o
    .io_input_payload     (datain_payload                        ), //i
    .io_output_valid      (streamCCByToggle_1_io_output_valid    ), //o
    .io_output_ready      (1'b1                                  ), //i
    .io_output_payload    (streamCCByToggle_1_io_output_payload  ), //o
    .clk_in               (clk_in                                ), //i
    .reset                (reset                                 ), //i
    .clk_out              (clk_out                               )  //i
  );
  assign datain_ready = streamCCByToggle_1_io_input_ready;
  assign dataout = streamCCByToggle_1_io_output_payload;

endmodule

module StreamCCByToggle (
  input               io_input_valid,
  output              io_input_ready,
  input      [15:0]   io_input_payload,
  output              io_output_valid,
  input               io_output_ready,
  output     [15:0]   io_output_payload,
  input               clk_in,
  input               reset,
  input               clk_out
);
  wire                outHitSignal_buffercc_io_dataOut;
  wire                pushArea_target_buffercc_io_dataOut;
  wire                outHitSignal;
  wire                pushArea_hit;
  wire                pushArea_accept;
  reg                 pushArea_target;
  reg        [15:0]   pushArea_data;
  wire                io_input_fire;
  wire                popArea_stream_valid;
  reg                 popArea_stream_ready;
  wire       [15:0]   popArea_stream_payload;
  wire                popArea_target;
  wire                popArea_stream_fire;
  reg                 popArea_hit;
  wire                popArea_stream_m2sPipe_valid;
  wire                popArea_stream_m2sPipe_ready;
  wire       [15:0]   popArea_stream_m2sPipe_payload;
  reg                 popArea_stream_rValid;
  wire                popArea_stream_fire_1;
  reg        [15:0]   popArea_stream_rData;
  wire                when_Stream_l342;

  BufferCC outHitSignal_buffercc (
    .io_dataIn     (outHitSignal                      ), //i
    .io_dataOut    (outHitSignal_buffercc_io_dataOut  ), //o
    .clk_in        (clk_in                            ), //i
    .reset         (reset                             )  //i
  );
  BufferCC_1 pushArea_target_buffercc (
    .io_dataIn     (pushArea_target                      ), //i
    .io_dataOut    (pushArea_target_buffercc_io_dataOut  ), //o
    .clk_out       (clk_out                              ), //i
    .reset         (reset                                )  //i
  );
  assign pushArea_hit = outHitSignal_buffercc_io_dataOut;
  assign io_input_fire = (io_input_valid && io_input_ready);
  assign pushArea_accept = io_input_fire;
  assign io_input_ready = (pushArea_hit == pushArea_target);
  assign popArea_target = pushArea_target_buffercc_io_dataOut;
  assign popArea_stream_fire = (popArea_stream_valid && popArea_stream_ready);
  assign outHitSignal = popArea_hit;
  assign popArea_stream_valid = (popArea_target != popArea_hit);
  assign popArea_stream_payload = pushArea_data;
  assign popArea_stream_fire_1 = (popArea_stream_valid && popArea_stream_ready);
  always @(*) begin
    popArea_stream_ready = popArea_stream_m2sPipe_ready;
    if(when_Stream_l342) begin
      popArea_stream_ready = 1'b1;
    end
  end

  assign when_Stream_l342 = (! popArea_stream_m2sPipe_valid);
  assign popArea_stream_m2sPipe_valid = popArea_stream_rValid;
  assign popArea_stream_m2sPipe_payload = popArea_stream_rData;
  assign io_output_valid = popArea_stream_m2sPipe_valid;
  assign popArea_stream_m2sPipe_ready = io_output_ready;
  assign io_output_payload = popArea_stream_m2sPipe_payload;
  always @(posedge clk_in or posedge reset) begin
    if(reset) begin
      pushArea_target <= 1'b0;
    end else begin
      if(pushArea_accept) begin
        pushArea_target <= (! pushArea_target);
      end
    end
  end

  always @(posedge clk_in) begin
    if(pushArea_accept) begin
      pushArea_data <= io_input_payload;
    end
  end

  always @(posedge clk_out or posedge reset) begin
    if(reset) begin
      popArea_hit <= 1'b0;
      popArea_stream_rValid <= 1'b0;
    end else begin
      if(popArea_stream_fire) begin
        popArea_hit <= popArea_target;
      end
      if(popArea_stream_ready) begin
        popArea_stream_rValid <= popArea_stream_valid;
      end
    end
  end

  always @(posedge clk_out) begin
    if(popArea_stream_fire_1) begin
      popArea_stream_rData <= popArea_stream_payload;
    end
  end


endmodule

module BufferCC_1 (
  input               io_dataIn,
  output              io_dataOut,
  input               clk_out,
  input               reset
);
  (* async_reg = "true" *) reg                 buffers_0;
  (* async_reg = "true" *) reg                 buffers_1;

  assign io_dataOut = buffers_1;
  always @(posedge clk_out or posedge reset) begin
    if(reset) begin
      buffers_0 <= 1'b0;
      buffers_1 <= 1'b0;
    end else begin
      buffers_0 <= io_dataIn;
      buffers_1 <= buffers_0;
    end
  end


endmodule

module BufferCC (
  input               io_dataIn,
  output              io_dataOut,
  input               clk_in,
  input               reset
);
  (* async_reg = "true" *) reg                 buffers_0;
  (* async_reg = "true" *) reg                 buffers_1;

  assign io_dataOut = buffers_1;
  always @(posedge clk_in or posedge reset) begin
    if(reset) begin
      buffers_0 <= 1'b0;
      buffers_1 <= 1'b0;
    end else begin
      buffers_0 <= io_dataIn;
      buffers_1 <= buffers_0;
    end
  end


endmodule

SPINAL_TEST/simWorkspace/DataSync/test.vcd
$version Generated by VerilatedVcd $end
$date Thu Sep 02 11:23:42 2021
 $end
$timescale   1ns $end

 $scope module TOP $end
  $var wire  1 =! clk_in $end
  $var wire  1 E! clk_out $end
  $var wire 16 e! datain_payload [15:0] $end
  $var wire  1 ]! datain_ready $end
  $var wire  1 U! datain_valid $end
  $var wire 16 m! dataout [15:0] $end
  $var wire  1 M! reset $end
  $scope module DataSync $end
   $var wire  1 =! clk_in $end
   $var wire  1 E! clk_out $end
   $var wire 16 e! datain_payload [15:0] $end
   $var wire  1 ]! datain_ready $end
   $var wire  1 U! datain_valid $end
   $var wire 16 m! dataout [15:0] $end
   $var wire  1 M! reset $end
   $var wire  1 ; streamCCByToggle_1_io_input_ready $end
   $var wire 16 K streamCCByToggle_1_io_output_payload [15:0] $end
   $var wire  1 S streamCCByToggle_1_io_output_valid $end
   $scope module streamCCByToggle_1 $end
    $var wire  1 =! clk_in $end
    $var wire  1 E! clk_out $end
    $var wire  1 C io_input_fire $end
    $var wire 16 e! io_input_payload [15:0] $end
    $var wire  1 ; io_input_ready $end
    $var wire  1 U! io_input_valid $end
    $var wire 16 K io_output_payload [15:0] $end
    $var wire  1 u! io_output_ready $end
    $var wire  1 S io_output_valid $end
    $var wire  1 %! outHitSignal $end
    $var wire  1 c outHitSignal_buffercc_io_dataOut $end
    $var wire  1 %! popArea_hit $end
    $var wire  1 3 popArea_stream_fire $end
    $var wire  1 3 popArea_stream_fire_1 $end
    $var wire 16 K popArea_stream_m2sPipe_payload [15:0] $end
    $var wire  1 u! popArea_stream_m2sPipe_ready $end
    $var wire  1 S popArea_stream_m2sPipe_valid $end
    $var wire 16 s popArea_stream_payload [15:0] $end
    $var wire 16 K popArea_stream_rData [15:0] $end
    $var wire  1 S popArea_stream_rValid $end
    $var wire  1 + popArea_stream_ready $end
    $var wire  1 # popArea_stream_valid $end
    $var wire  1 { popArea_target $end
    $var wire  1 C pushArea_accept $end
    $var wire 16 s pushArea_data [15:0] $end
    $var wire  1 c pushArea_hit $end
    $var wire  1 5! pushArea_target $end
    $var wire  1 { pushArea_target_buffercc_io_dataOut $end
    $var wire  1 M! reset $end
    $var wire  1 [ when_Stream_l342 $end
    $scope module outHitSignal_buffercc $end
     $var wire  1 k buffers_0 $end
     $var wire  1 c buffers_1 $end
     $var wire  1 =! clk_in $end
     $var wire  1 %! io_dataIn $end
     $var wire  1 c io_dataOut $end
     $var wire  1 M! reset $end
    $upscope $end
    $scope module pushArea_target_buffercc $end
     $var wire  1 -! buffers_0 $end
     $var wire  1 { buffers_1 $end
     $var wire  1 E! clk_out $end
     $var wire  1 5! io_dataIn $end
     $var wire  1 { io_dataOut $end
     $var wire  1 M! reset $end
    $upscope $end
   $upscope $end
  $upscope $end
 $upscope $end
$enddefinitions $end


#0
0#
1+
03
1;
1C
b1110110011111000 K
0S
1[
0c
0k
b1001010000010010 s
0{
0%!
0-!
05!
0=!
0E!
1M!
1U!
1]!
b1011111001100110 e!
b1110110011111000 m!
1u!
#160
0M!
#170
1E!
#175
0E!
#180
1E!
#185
0E!
#190
1E!
#195
0E!
#200
1E!
#205
0E!
#210
1E!
#215
0E!
#220
1E!
#225
0E!
#230
1E!
#235
0E!
#240
1E!
#245
0E!
#250
1E!
#255
0E!
#260
1E!
#265
0E!
#270
1E!
#275
0E!
#280
1E!
#285
0E!
#290
1E!
#295
0E!
#300
1E!
#305
0E!
#310
1E!
#315
0E!
#320
1E!
#325
0E!
#330
1E!
#335
0E!
#340
0;
0C
b1011111001100110 s
15!
1=!
1E!
0]!
#345
0E!
#350
1-!
0=!
1E!
#355
0E!
#360
1#
13
1{
1=!
1E!
#365
0E!
#370
0#
03
b1011111001100110 K
1S
0[
1%!
0=!
1E!
b1011111001100110 m!
#375
0E!
#380
0S
1[
1k
1=!
1E!
#385
0E!
#390
0=!
1E!
#395
0E!
#400
1;
1C
1c
1=!
1E!
1]!
#405
0E!
#410
0=!
1E!
#415
0E!
#420
0;
0C
05!
1=!
1E!
0]!
#425
0E!
#430
0-!
0=!
1E!
#435
0E!
#440
1#
13
0{
1=!
1E!
#445
0E!
#450
0#
03
1S
0[
0%!
0=!
1E!
#455
0E!
#460
0S
1[
0k
1=!
1E!
#465
0E!
#470
0=!
1E!
#475
0E!
#480
1;
1C
0c
1=!
1E!
1]!
#485
0E!
#490
0=!
1E!
#495
0E!
#500
0;
0C
15!
1=!
1E!
0]!
#505
0E!
#510
1-!
0=!
1E!
#515
0E!
#520
1#
13
1{
1=!
1E!
#525
0E!
#530
0#
03
1S
0[
1%!
0=!
1E!
#535
0E!
#540
0S
1[
1k
1=!
1E!
#545
0E!
#550
0=!
1E!
#555
0E!
#560
1;
1C
1c
1=!
1E!
1]!
#565
0E!
#570
0=!
1E!
#575
0E!
#580
0;
0C
05!
1=!
1E!
0]!
#585
0E!
#590
0-!
0=!
1E!
#595
0E!
#600
1#
13
0{
1=!
1E!
#605
0E!
#610
0#
03
1S
0[
0%!
0=!
1E!
#615
0E!
#620
0S
1[
0k
1=!
1E!
#625
0E!
#630
0=!
1E!
#635
0E!
#640
1;
1C
0c
1=!
1E!
1]!
#645
0E!
#650
0=!
1E!
#655
0E!
#660
0;
0C
15!
1=!
1E!
0]!
#665
0E!
#670
1-!
0=!
1E!
#675
0E!
#680
1#
13
1{
1=!
1E!
#685
0E!
#690
0#
03
1S
0[
1%!
0=!
1E!
#695
0E!
#700
0S
1[
1k
1=!
1E!
#705
0E!
#710
0=!
1E!
#715
0E!
#720
1;
1C
1c
1=!
1E!
1]!
b0000000011001000 e!
#725
0E!
#730
0=!
1E!
#735
0E!
#740
0;
0C
b0000000011001000 s
05!
1=!
1E!
0]!
#745
0E!
#750
0-!
0=!
1E!
#755
0E!
#760
1#
13
0{
1=!
1E!
#765
0E!
#770
0#
03
b0000000011001000 K
1S
0[
0%!
0=!
1E!
b0000000011001000 m!
#775
0E!
#780
0S
1[
0k
1=!
1E!
#785
0E!
#790
0=!
1E!
#795
0E!
#800
1;
1C
0c
1=!
1E!
1]!
#805
0E!
#810
0=!
1E!
#815
0E!
#820
0;
0C
15!
1=!
1E!
0]!
#825
0E!
#830
1-!
0=!
1E!
#835
0E!
#840
1#
13
1{
1=!
1E!
#845
0E!
#850
0#
03
1S
0[
1%!
0=!
1E!
#855
0E!
#860
0S
1[
1k
1=!
1E!
#865
0E!
#870
0=!
1E!
#875
0E!
#880
1;
1C
1c
1=!
1E!
1]!
#885
0E!
#890
0=!
1E!
#895
0E!
#900
0;
0C
05!
1=!
1E!
0]!
#905
0E!
#910
0-!
0=!
1E!
#915
0E!
#920
1#
13
0{
1=!
1E!
#925
0E!
#930
0#
03
1S
0[
0%!
0=!
1E!
#935
0E!
#940
0S
1[
0k
1=!
1E!
b0000000011011011 e!
#945
0E!
#950
0=!
1E!
#955
0E!
#960
1;
1C
0c
1=!
1E!
1]!
#965
0E!
#970
0=!
1E!
#975
0E!
#980
0;
0C
b0000000011011011 s
15!
1=!
1E!
0]!
#985
0E!
#990
1-!
0=!
1E!
#995
0E!
#1000
1#
13
1{
1=!
1E!
#1005
0E!
#1010
0#
03
b0000000011011011 K
1S
0[
1%!
0=!
1E!
b0000000011011011 m!
#1015
0E!
#1020
0S
1[
1k
1=!
1E!
#1025
0E!
#1030
0=!
1E!
#1035
0E!
#1040
1;
1C
1c
1=!
1E!
1]!
#1045
0E!
#1050
0=!
1E!
#1055
0E!
#1060
0;
0C
05!
1=!
1E!
0]!
#1065
0E!
#1070
0-!
0=!
1E!
#1075
0E!
#1080
1#
13
0{
1=!
1E!
#1085
0E!
#1090
0#
03
1S
0[
0%!
0=!
1E!
#1095
0E!
#1100
0S
1[
0k
1=!
1E!
#1105
0E!
#1110
0=!
1E!
#1115
0E!
#1120
1;
1C
0c
1=!
1E!
1]!
#1125
0E!
#1130
0=!
1E!
#1135
0E!
#1140
0;
0C
15!
1=!
1E!
0]!
#1145
0E!
#1150
1-!
0=!
1E!
#1155
0E!
#1160
1#
13
1{
1=!
1E!
b0000000010011111 e!
#1165
0E!
#1170
0#
03
1S
0[
1%!
0=!
1E!
#1175
0E!
#1180
0S
1[
1k
1=!
1E!
#1185
0E!
#1190
0=!
1E!
#1195
0E!
#1200
1;
1C
1c
1=!
1E!
1]!
#1205
0E!
#1210
0=!
1E!
#1215
0E!
#1220
0;
0C
b0000000010011111 s
05!
1=!
1E!
0]!
#1225
0E!
#1230
0-!
0=!
1E!
#1235
0E!
#1240
1#
13
0{
1=!
1E!
#1245
0E!
#1250
0#
03
b0000000010011111 K
1S
0[
0%!
0=!
1E!
b0000000010011111 m!
#1255
0E!
#1260
0S
1[
0k
1=!
1E!
#1265
0E!
#1270
0=!
1E!
#1275
0E!
#1280
1;
1C
0c
1=!
1E!
1]!
#1285
0E!
#1290
0=!
1E!
#1295
0E!
#1300
0;
0C
15!
1=!
1E!
0]!
#1305
0E!
#1310
1-!
0=!
1E!
#1315
0E!
#1320
1#
13
1{
1=!
1E!
#1325
0E!
#1330
0#
03
1S
0[
1%!
0=!
1E!
#1335
0E!
#1340
0S
1[
1k
1=!
1E!
#1345
0E!
#1350
0=!
1E!
#1355
0E!
#1360
1;
1C
1c
1=!
1E!
1]!
#1365
0E!
#1370
0=!
1E!
#1375
0E!
#1380
0;
0C
05!
1=!
1E!
0]!
b0000000011100011 e!
#1385
0E!
#1390
0-!
0=!
1E!
#1395
0E!
#1400
1#
13
0{
1=!
1E!
#1405
0E!
#1410
0#
03
1S
0[
0%!
0=!
1E!
#1415
0E!
#1420
0S
1[
0k
1=!
1E!
#1425
0E!
#1430
0=!
1E!
#1435
0E!
#1440
1;
1C
0c
1=!
1E!
1]!
#1445
0E!
#1450
0=!
1E!
#1455
0E!
#1460
0;
0C
b0000000011100011 s
15!
1=!
1E!
0]!
#1465
0E!
#1470
1-!
0=!
1E!
#1475
0E!
#1480
1#
13
1{
1=!
1E!
#1485
0E!
#1490
0#
03
b0000000011100011 K
1S
0[
1%!
0=!
1E!
b0000000011100011 m!
#1495
0E!
#1500
0S
1[
1k
1=!
1E!
#1505
0E!
#1510
0=!
1E!
#1515
0E!
#1520
1;
1C
1c
1=!
1E!
1]!
#1525
0E!
#1530
0=!
1E!
#1535
0E!
#1540
0;
0C
05!
1=!
1E!
0]!
#1545
0E!
#1550
0-!
0=!
1E!
#1555
0E!
#1560
1#
13
0{
1=!
1E!
#1565
0E!
#1570
0#
03
1S
0[
0%!
0=!
1E!
#1575
0E!
#1580
0S
1[
0k
1=!
1E!
#1585
0E!
#1590
0=!
1E!
#1595
0E!
#1600
1;
1C
0c
1=!
1E!
1]!
b0000000001010111 e!
#1605
0E!
#1610
0=!
1E!
#1615
0E!
#1620
0;
0C
b0000000001010111 s
15!
1=!
1E!
0]!
#1625
0E!
#1630
1-!
0=!
1E!
#1635
0E!
#1640
1#
13
1{
1=!
1E!
#1645
0E!
#1650
0#
03
b0000000001010111 K
1S
0[
1%!
0=!
1E!
b0000000001010111 m!
#1655
0E!
#1660
0S
1[
1k
1=!
1E!
#1665
0E!
#1670
0=!
1E!
#1675
0E!
#1680
1;
1C
1c
1=!
1E!
1]!
#1685
0E!
#1690
0=!
1E!
#1695
0E!
#1700
0;
0C
05!
1=!
1E!
0]!
#1705
0E!
#1710
0-!
0=!
1E!
#1715
0E!
#1720
1#
13
0{
1=!
1E!
#1725
0E!
#1730
0#
03
1S
0[
0%!
0=!
1E!
#1735
0E!
#1740
0S
1[
0k
1=!
1E!
#1745
0E!
#1750
0=!
1E!
#1755
0E!
#1760
1;
1C
0c
1=!
1E!
1]!
#1765
0E!
#1770
0=!
1E!
#1775
0E!
#1780
0;
0C
15!
1=!
1E!
0]!
#1785
0E!
#1790
1-!
0=!
1E!
#1795
0E!
#1800
1#
13
1{
1=!
1E!
#1805
0E!
#1810
0#
03
1S
0[
1%!
0=!
1E!
#1815
0E!
#1820
0S
1[
1k
1=!
1E!
b0000000000110010 e!
#1825
0E!
#1830
0=!
1E!
#1835
0E!
#1840
1;
1C
1c
1=!
1E!
1]!
#1845
0E!
#1850
0=!
1E!
#1855
0E!
#1860
0;
0C
b0000000000110010 s
05!
1=!
1E!
0]!
#1865
0E!
#1870
0-!
0=!
1E!
#1875
0E!
#1880
1#
13
0{
1=!
1E!
#1885
0E!
#1890
0#
03
b0000000000110010 K
1S
0[
0%!
0=!
1E!
b0000000000110010 m!
#1895
0E!
#1900
0S
1[
0k
1=!
1E!
#1905
0E!
#1910
0=!
1E!
#1915
0E!
#1920
1;
1C
0c
1=!
1E!
1]!
#1925
0E!
#1930
0=!
1E!
#1935
0E!
#1940
0;
0C
15!
1=!
1E!
0]!
#1945
0E!
#1950
1-!
0=!
1E!
#1955
0E!
#1960
1#
13
1{
1=!
1E!
#1965
0E!
#1970
0#
03
1S
0[
1%!
0=!
1E!
#1975
0E!
#1980
0S
1[
1k
1=!
1E!
#1985
0E!
#1990
0=!
1E!
#1995
0E!
#2000
1;
1C
1c
1=!
1E!
1]!
#2005
0E!
#2010
0=!
1E!
#2015
0E!
#2020
0;
0C
05!
1=!
1E!
0]!
#2025
0E!
#2030
0-!
0=!
1E!
#2035
0E!
#2040
1#
13
0{
1=!
1E!
b0000000010100101 e!
#2045
0E!
#2050
0#
03
1S
0[
0%!
0=!
1E!
#2055
0E!
#2060
0S
1[
0k
1=!
1E!
#2065
0E!
#2070
0=!
1E!
#2075
0E!
#2080
1;
1C
0c
1=!
1E!
1]!
#2085
0E!
#2090
0=!
1E!
#2095
0E!
#2100
0;
0C
b0000000010100101 s
15!
1=!
1E!
0]!
#2105
0E!
#2110
1-!
0=!
1E!
#2115
0E!
#2120
1#
13
1{
1=!
1E!
#2125
0E!
#2130
0#
03
b0000000010100101 K
1S
0[
1%!
0=!
1E!
b0000000010100101 m!
#2135
0E!
#2140
0S
1[
1k
1=!
1E!
#2145
0E!
#2150
0=!
1E!
#2155
0E!
#2160
1;
1C
1c
1=!
1E!
1]!
#2165
0E!
#2170
0=!
1E!
#2175
0E!
#2180
0;
0C
05!
1=!
1E!
0]!
#2185
0E!
#2190
0-!
0=!
1E!
#2195
0E!
#2200
1#
13
0{
1=!
1E!
#2205
0E!
#2210
0#
03
1S
0[
0%!
0=!
1E!
#2215
0E!
#2220
0S
1[
0k
1=!
1E!
#2225
0E!
#2230
0=!
1E!
#2235
0E!
#2240
1;
1C
0c
1=!
1E!
1]!
#2245
0E!
#2250
0=!
1E!
#2255
0E!
#2260
0;
0C
15!
1=!
1E!
0]!
b0000000000110101 e!
#2265
0E!
#2270
1-!
0=!
1E!
#2275
0E!
#2280
1#
13
1{
1=!
1E!
#2285
0E!
#2290
0#
03
1S
0[
1%!
0=!
1E!
#2295
0E!
#2300
0S
1[
1k
1=!
1E!
#2305
0E!
#2310
0=!
1E!
#2315
0E!
#2320
1;
1C
1c
1=!
1E!
1]!
#2325
0E!
#2330
0=!
1E!
#2335
0E!
#2340
0;
0C
b0000000000110101 s
05!
1=!
1E!
0]!
#2345
0E!
#2350
0-!
0=!
1E!
#2355
0E!
#2360
1#
13
0{
1=!
1E!
#2365
0E!
#2370
0#
03
b0000000000110101 K
1S
0[
0%!
0=!
1E!
b0000000000110101 m!
#2375
0E!
#2380
0S
1[
0k
1=!
1E!
#2385
0E!
#2390
0=!
1E!
#2395
0E!
#2400
1;
1C
0c
1=!
1E!
1]!
#2405
0E!
#2410
0=!
1E!
#2415
0E!
#2420
0;
0C
15!
1=!
1E!
0]!
#2425
0E!
#2430
1-!
0=!
1E!
#2435
0E!
#2440
1#
13
1{
1=!
1E!
#2445
0E!
#2450
0#
03
1S
0[
1%!
0=!
1E!
#2455
0E!
#2460
0S
1[
1k
1=!
1E!
#2465
0E!
#2470
0=!
1E!
#2475
0E!
#2480
1;
1C
1c
1=!
1E!
1]!
b0000000011100000 e!
#2485
0E!
#2490
0=!
1E!
#2495
0E!
#2500
0;
0C
b0000000011100000 s
05!
1=!
1E!
0]!
#2505
0E!
#2510
0-!
0=!
1E!
#2515
0E!
#2520
1#
13
0{
1=!
1E!
#2525
0E!
#2530
0#
03
b0000000011100000 K
1S
0[
0%!
0=!
1E!
b0000000011100000 m!
#2535
0E!
#2540
0S
1[
0k
1=!
1E!
#2545
0E!
#2550
0=!
1E!
#2555
0E!
#2560
1;
1C
0c
1=!
1E!
1]!
#2565
0E!
#2570
0=!
1E!
#2575
0E!
#2580
0;
0C
15!
1=!
1E!
0]!
#2585
0E!
#2590
1-!
0=!
1E!
#2595
0E!
#2600
1#
13
1{
1=!
1E!
#2605
0E!
#2610
0#
03
1S
0[
1%!
0=!
1E!
#2615
0E!
#2620
0S
1[
1k
1=!
1E!
#2625
0E!
#2630
0=!
1E!
#2635
0E!
#2640
1;
1C
1c
1=!
1E!
1]!
#2645
0E!
#2650
0=!
1E!
#2655
0E!
#2660
0;
0C
05!
1=!
1E!
0]!
#2665
0E!
#2670
0-!
0=!
1E!
#2675
0E!
#2680
1#
13
0{
1=!
1E!
#2685
0E!
#2690
0#
03
1S
0[
0%!
0=!
1E!
#2695
0E!
#2700
0S
1[
0k
1=!
1E!
b0000000011000001 e!
#2705
0E!
#2710
0=!
1E!
#2715
0E!
#2720
1;
1C
0c
1=!
1E!
1]!
#2725
0E!
#2730
0=!
1E!
#2735
0E!
#2740
0;
0C
b0000000011000001 s
15!
1=!
1E!
0]!
#2745
0E!
#2750
1-!
0=!
1E!
#2755
0E!
#2760
1#
13
1{
1=!
1E!
#2765
0E!
#2770
0#
03
b0000000011000001 K
1S
0[
1%!
0=!
1E!
b0000000011000001 m!
#2775
0E!
#2780
0S
1[
1k
1=!
1E!
#2785
0E!
#2790
0=!
1E!
#2795
0E!
#2800
1;
1C
1c
1=!
1E!
1]!
#2805
0E!
#2810
0=!
1E!
#2815
0E!
#2820
0;
0C
05!
1=!
1E!
0]!
#2825
0E!
#2830
0-!
0=!
1E!
#2835
0E!
#2840
1#
13
0{
1=!
1E!
#2845
0E!
#2850
0#
03
1S
0[
0%!
0=!
1E!
#2855
0E!
#2860
0S
1[
0k
1=!
1E!
#2865
0E!
#2870
0=!
1E!
#2875
0E!
#2880
1;
1C
0c
1=!
1E!
1]!
#2885
0E!
#2890
0=!
1E!
#2895
0E!
#2900
0;
0C
15!
1=!
1E!
0]!
#2905
0E!
#2910
1-!
0=!
1E!
#2915
0E!
#2920
1#
13
1{
1=!
1E!
b0000000010000101 e!
#2925
0E!
#2930
0#
03
1S
0[
1%!
0=!
1E!
#2935
0E!
#2940
0S
1[
1k
1=!
1E!
#2945
0E!
#2950
0=!
1E!
#2955
0E!
#2960
1;
1C
1c
1=!
1E!
1]!
#2965
0E!
#2970
0=!
1E!
#2975
0E!
#2980
0;
0C
b0000000010000101 s
05!
1=!
1E!
0]!
#2985
0E!
#2990
0-!
0=!
1E!
#2995
0E!
#3000
1#
13
0{
1=!
1E!
#3005
0E!
#3010
0#
03
b0000000010000101 K
1S
0[
0%!
0=!
1E!
b0000000010000101 m!
#3015
0E!
#3020
0S
1[
0k
1=!
1E!
#3025
0E!
#3030
0=!
1E!
#3035
0E!
#3040
1;
1C
0c
1=!
1E!
1]!
#3045
0E!
#3050
0=!
1E!
#3055
0E!
#3060
0;
0C
15!
1=!
1E!
0]!
#3065
0E!
#3070
1-!
0=!
1E!
#3075
0E!
#3080
1#
13
1{
1=!
1E!
#3085
0E!
#3090
0#
03
1S
0[
1%!
0=!
1E!
#3095
0E!
#3100
0S
1[
1k
1=!
1E!
#3105
0E!
#3110
0=!
1E!
#3115
0E!
#3120
1;
1C
1c
1=!
1E!
1]!
#3125
0E!
#3130
0=!
1E!
#3135
0E!
#3140
0;
0C
05!
1=!
1E!
0]!
b0000000000011100 e!
#3145
0E!
#3150
0-!
0=!
1E!
#3155
0E!
#3160
1#
13
0{
1=!
1E!
#3165
0E!
#3170
0#
03
1S
0[
0%!
0=!
1E!
#3175
0E!
#3180
0S
1[
0k
1=!
1E!
#3185
0E!
#3190
0=!
1E!
#3195
0E!
#3200
1;
1C
0c
1=!
1E!
1]!
#3205
0E!
#3210
0=!
1E!
#3215
0E!
#3220
0;
0C
b0000000000011100 s
15!
1=!
1E!
0]!
#3225
0E!
#3230
1-!
0=!
1E!
#3235
0E!
#3240
1#
13
1{
1=!
1E!
#3245
0E!
#3250
0#
03
b0000000000011100 K
1S
0[
1%!
0=!
1E!
b0000000000011100 m!
#3255
0E!
#3260
0S
1[
1k
1=!
1E!
#3265
0E!
#3270
0=!
1E!
#3275
0E!
#3280
1;
1C
1c
1=!
1E!
1]!
#3285
0E!
#3290
0=!
1E!
#3295
0E!
#3300
0;
0C
05!
1=!
1E!
0]!
#3305
0E!
#3310
0-!
0=!
1E!
#3315
0E!
#3320
1#
13
0{
1=!
1E!
#3325
0E!
#3330
0#
03
1S
0[
0%!
0=!
1E!
#3335
0E!
#3340
0S
1[
0k
1=!
1E!
#3345
0E!
#3350
0=!
1E!
#3355
0E!
#3360
1;
1C
0c
1=!
1E!
1]!
b0000000000101001 e!
#3365
0E!
#3370
0=!
1E!
#3375
0E!
#3380
0;
0C
b0000000000101001 s
15!
1=!
1E!
0]!
#3385
0E!
#3390
1-!
0=!
1E!
#3395
0E!
#3400
1#
13
1{
1=!
1E!
#3405
0E!
#3410
0#
03
b0000000000101001 K
1S
0[
1%!
0=!
1E!
b0000000000101001 m!
#3415
0E!
#3420
0S
1[
1k
1=!
1E!
#3425
0E!
#3430
0=!
1E!
#3435
0E!
#3440
1;
1C
1c
1=!
1E!
1]!
#3445
0E!
#3450
0=!
1E!
#3455
0E!
#3460
0;
0C
05!
1=!
1E!
0]!
#3465
0E!
#3470
0-!
0=!
1E!
#3475
0E!
#3480
1#
13
0{
1=!
1E!
#3485
0E!
#3490
0#
03
1S
0[
0%!
0=!
1E!
#3495
0E!
#3500
0S
1[
0k
1=!
1E!
#3505
0E!
#3510
0=!
1E!
#3515
0E!
#3520
1;
1C
0c
1=!
1E!
1]!
#3525
0E!
#3530
0=!
1E!
#3535
0E!
#3540
0;
0C
15!
1=!
1E!
0]!
#3545
0E!
#3550
1-!
0=!
1E!
#3555
0E!
#3560
1#
13
1{
1=!
1E!
#3565
0E!
#3570
0#
03
1S
0[
1%!
0=!
1E!
#3575
0E!
#3580
0S
1[
1k
1=!
1E!
b0000000000000000 e!
#3585
0E!
#3590
0=!
1E!
#3595
0E!
#3600
1;
1C
1c
1=!
1E!
1]!
#3605
0E!
#3610
0=!
1E!
#3615
0E!
#3620
0;
0C
b0000000000000000 s
05!
1=!
1E!
0]!
#3625
0E!
#3630
0-!
0=!
1E!
#3635
0E!
#3640
1#
13
0{
1=!
1E!
#3645
0E!
#3650
0#
03
b0000000000000000 K
1S
0[
0%!
0=!
1E!
b0000000000000000 m!
#3655
0E!
#3660
0S
1[
0k
1=!
1E!
#3665
0E!
#3670
0=!
1E!
#3675
0E!
#3680
1;
1C
0c
1=!
1E!
1]!
#3685
0E!
#3690
0=!
1E!
#3695
0E!
#3700
0;
0C
15!
1=!
1E!
0]!
#3705
0E!
#3710
1-!
0=!
1E!
#3715
0E!
#3720
1#
13
1{
1=!
1E!
#3725
0E!
#3730
0#
03
1S
0[
1%!
0=!
1E!
#3735
0E!
#3740
0S
1[
1k
1=!
1E!
#3745
0E!
#3750
0=!
1E!
#3755
0E!
#3760
1;
1C
1c
1=!
1E!
1]!
#3765
0E!
#3770
0=!
1E!
#3775
0E!
#3780
0;
0C
05!
1=!
1E!
0]!
#3785
0E!
#3790
0-!
0=!
1E!
#3795
0E!
#3800
1#
13
0{
1=!
1E!
b0000000001011110 e!
#3805
0E!
#3810
0#
03
1S
0[
0%!
0=!
1E!
#3815
0E!
#3820
0S
1[
0k
1=!
1E!
#3825
0E!
#3830
0=!
1E!
#3835
0E!
#3840
1;
1C
0c
1=!
1E!
1]!
#3845
0E!
#3850
0=!
1E!
#3855
0E!
#3860
0;
0C
b0000000001011110 s
15!
1=!
1E!
0]!
#3865
0E!
#3870
1-!
0=!
1E!
#3875
0E!
#3880
1#
13
1{
1=!
1E!
#3885
0E!
#3890
0#
03
b0000000001011110 K
1S
0[
1%!
0=!
1E!
b0000000001011110 m!
#3895
0E!
#3900
0S
1[
1k
1=!
1E!
#3905
0E!
#3910
0=!
1E!
#3915
0E!
#3920
1;
1C
1c
1=!
1E!
1]!
#3925
0E!
#3930
0=!
1E!
#3935
0E!
#3940
0;
0C
05!
1=!
1E!
0]!
#3945
0E!
#3950
0-!
0=!
1E!
